digitallab/__init__.py
digitallab/lab.py
digitallab/evaluation/__init__.py
digitallab/evaluation/data_processing/__init__.py
digitallab/evaluation/data_processing/all_experiments_database_collector.py
digitallab/evaluation/data_processing/database_collector_interface.py
digitallab/evaluation/data_processing/facetoface_database_collector.py
digitallab/evaluation/data_processing/procedural_columns.py
digitallab/evaluation/data_processing/procedural_database_collector.py
digitallab/evaluation/data_retrieval/__init__.py
digitallab/evaluation/data_retrieval/cache.py
digitallab/evaluation/data_retrieval/retrieval.py
digitallab/evaluation/helper/__init__.py
digitallab/evaluation/helper/filter.py
digitallab/evaluation/helper/flatten.py
digitallab/evaluation/plots/__init__.py
digitallab/evaluation/plots/aggregate_plot_skeleton.py
digitallab/evaluation/plots/box_plot.py
digitallab/evaluation/plots/ecdf_plot.py
digitallab/evaluation/plots/facetoface_density_bar_plot.py
digitallab/evaluation/plots/facetoface_plot_skeleton.py
digitallab/evaluation/plots/plot_skeleton.py
digitallab/evaluation/tables/__init__.py
digitallab/evaluation/tables/table_skeleton.py
digitallab/evaluation/tables/tables.py
digitallab/helper/__init__.py
digitallab/helper/chunks.py
digitallab/helper/conversion.py
digitallab/helper/database_interface.py
digitallab/helper/db_access.py
digitallab/helper/experiment_setting.py
digitallab/helper/experiment_validation.py
digitallab/helper/generate_seeds.py
digitallab/helper/optionals.py
digitallab/helper/output.py
digitallab/helper/singleton.py
digitallab/helper/storage.py
digitallab/helper/tinydb_access_register.py
digitallab/tests/__init__.py
digitallab/tests/cleanup.py
digitallab/tests/experiments_for_tests.py
digitallab/tests/generate_reference_plots.py
digitallab/tests/test_box_plot.py
digitallab/tests/test_chunks.py
digitallab/tests/test_database_interface.py
digitallab/tests/test_ecdf_plot.py
digitallab/tests/test_experiment_setting.py
digitallab-1.4.3.3.dist-info/LICENSE
digitallab-1.4.3.3.dist-info/METADATA
digitallab-1.4.3.3.dist-info/WHEEL
digitallab-1.4.3.3.dist-info/top_level.txt
digitallab-1.4.3.3.dist-info/RECORD
