Metadata-Version: 2.1
Name: digitallab
Version: 1.4.3.3
Summary: digitallab is a python package for conducting large-scale computational experiments.
Home-page: https://gitlab.com/Dnis/dlab
Author: Dennis Kreber
Author-email: dnis.kk@gmail.com
License: UNKNOWN
Platform: UNKNOWN
Classifier: Programming Language :: Python :: 3
Classifier: License :: OSI Approved :: MIT License
Classifier: Operating System :: OS Independent
Requires-Python: >=3.6
License-File: LICENSE
Requires-Dist: numpy
Requires-Dist: pandas
Requires-Dist: tqdm
Requires-Dist: pymongo
Requires-Dist: sacred
Requires-Dist: seaborn
Requires-Dist: matplotlib
Requires-Dist: tables
Requires-Dist: pick
